rnc2rng/__init__.py
rnc2rng/__main__.py
rnc2rng/parser.py
rnc2rng/rnctree.py
rnc2rng/serializer.py
rnc2rng-2.7.0.dist-info/AUTHORS
rnc2rng-2.7.0.dist-info/LICENSE
rnc2rng-2.7.0.dist-info/METADATA
rnc2rng-2.7.0.dist-info/WHEEL
rnc2rng-2.7.0.dist-info/entry_points.txt
rnc2rng-2.7.0.dist-info/top_level.txt
rnc2rng-2.7.0.dist-info/RECORD
