Metadata-Version: 2.1
Name: rnc2rng
Version: 2.7.0
Summary: RELAX NG Compact to regular syntax conversion library
Home-page: https://github.com/djc/rnc2rng
Author: David Mertz
Maintainer: Dirkjan Ochtman
Maintainer-email: dirkjan@ochtman.nl
Classifier: Development Status :: 5 - Production/Stable
Classifier: Intended Audience :: Developers
Classifier: Operating System :: OS Independent
Classifier: License :: OSI Approved :: MIT License
Classifier: Topic :: Text Processing :: Markup :: XML
Classifier: Programming Language :: Python :: 3
Classifier: Programming Language :: Python :: 3.7
Classifier: Programming Language :: Python :: 3.8
Classifier: Programming Language :: Python :: 3.9
License-File: LICENSE
License-File: AUTHORS
Requires-Dist: rply
